eggnog_mapper-2.1.13.data/scripts/create_dbs.py
eggnog_mapper-2.1.13.data/scripts/download_eggnog_data.py
eggnog_mapper-2.1.13.data/scripts/emapper.py
eggnog_mapper-2.1.13.data/scripts/hmm_mapper.py
eggnog_mapper-2.1.13.data/scripts/hmm_server.py
eggnog_mapper-2.1.13.data/scripts/hmm_worker.py
eggnog_mapper-2.1.13.dist-info/licenses/LICENSE.txt
eggnogmapper/__init__.py
eggnogmapper/common.py
eggnogmapper/emapper.py
eggnogmapper/emapperException.py
eggnogmapper/hmm_mapper.py
eggnogmapper/utils.py
eggnogmapper/version.py
eggnogmapper/annotation/__init__.py
eggnogmapper/annotation/annota.py
eggnogmapper/annotation/annota_mongo.py
eggnogmapper/annotation/annotator.py
eggnogmapper/annotation/annotator_novel_fams.py
eggnogmapper/annotation/annotator_worker.py
eggnogmapper/annotation/annotator_worker_novel_fams.py
eggnogmapper/annotation/annotators.py
eggnogmapper/annotation/cache_annotator.py
eggnogmapper/annotation/db_sqlite.py
eggnogmapper/annotation/orthologs.py
eggnogmapper/annotation/output.py
eggnogmapper/annotation/output_novel_fams.py
eggnogmapper/annotation/ncbitaxa/__init__.py
eggnogmapper/annotation/ncbitaxa/ncbiquery.py
eggnogmapper/annotation/pfam/__init__.py
eggnogmapper/annotation/pfam/pfam.py
eggnogmapper/annotation/pfam/pfam_common.py
eggnogmapper/annotation/pfam/pfam_denovo.py
eggnogmapper/annotation/pfam/pfam_modes.py
eggnogmapper/annotation/pfam/pfam_scan.py
eggnogmapper/annotation/pfam/pfam_search.py
eggnogmapper/annotation/tax_scopes/__init__.py
eggnogmapper/annotation/tax_scopes/all
eggnogmapper/annotation/tax_scopes/all_broad
eggnogmapper/annotation/tax_scopes/all_narrow
eggnogmapper/annotation/tax_scopes/archaea
eggnogmapper/annotation/tax_scopes/auto
eggnogmapper/annotation/tax_scopes/auto_broad
eggnogmapper/annotation/tax_scopes/bacteria
eggnogmapper/annotation/tax_scopes/bacteria_broad
eggnogmapper/annotation/tax_scopes/eukaryota
eggnogmapper/annotation/tax_scopes/eukaryota_broad
eggnogmapper/annotation/tax_scopes/prokaryota_broad
eggnogmapper/annotation/tax_scopes/tax_scopes.py
eggnog_mapper-2.1.13.dist-info/METADATA
eggnog_mapper-2.1.13.dist-info/WHEEL
eggnog_mapper-2.1.13.dist-info/top_level.txt
eggnog_mapper-2.1.13.dist-info/RECORD
