Metadata-Version: 2.4
Name: eggnog-mapper
Version: 2.1.13
Summary: Fast functional annotation of novel sequences using eggNOG orthology assignments.
Home-page: http://eggnog-mapper.embl.de
Author: Jaime Huerta-Cepas
Author-email: jhcepas@gmail.com
Maintainer: Jaime Huerta-Cepas
Maintainer-email: huerta@embl.de
License: GPLv3
Keywords: functional annotation,orthology,eggNOG
Platform: OS Independent
Classifier: Environment :: Console
Classifier: Intended Audience :: Science/Research
Classifier: License :: OSI Approved :: GNU General Public License (GPL)
Classifier: Natural Language :: English
Classifier: Operating System :: MacOS
Classifier: Operating System :: Microsoft :: Windows
Classifier: Operating System :: POSIX :: Linux
Classifier: Programming Language :: Python
Classifier: Programming Language :: Python :: 3.7
Classifier: Topic :: Scientific/Engineering :: Bio-Informatics
Classifier: Topic :: Software Development :: Libraries :: Python Modules
Requires-Python: >=3.7
License-File: LICENSE.txt
Requires-Dist: biopython==1.76
Requires-Dist: psutil==5.7.0
Requires-Dist: xlsxwriter==1.4.3
Dynamic: license-file
